{
  "content_type": "CGSHOP2026_Instance",
  "instance_uid": "random_instance_36_80_3-coreset",
  "points_x": [
    142,
    394,
    2150,
    1165,
    2630,
    1732,
    2945,
    213,
    1614,
    921,
    1551,
    638,
    843,
    2220,
    2402,
    276,
    2189,
    1488,
    2528,
    709,
    606,
    2244,
    2087,
    2276,
    1843,
    1488,
    480,
    2787,
    2937,
    1843,
    677,
    1614,
    63,
    2331,
    638,
    3016,
    213,
    1000,
    1614,
    1488,
    2756,
    709,
    2118,
    669,
    2835,
    2528,
    1780,
    1551,
    2496,
    2559,
    480,
    2787,
    1197,
    1843,
    1417,
    394,
    1921,
    3055,
    2276,
    638,
    1425,
    1614,
    2346,
    677,
    843,
    1362,
    3087,
    921,
    638,
    276,
    606,
    362,
    1811,
    2118,
    1551,
    890,
    1425,
    528,
    1362,
    480
  ],
  "points_y": [
    370,
    69,
    2544,
    370,
    630,
    2851,
    2063,
    69,
    3316,
    2544,
    496,
    654,
    2835,
    630,
    1488,
    1961,
    1536,
    1827,
    1276,
    2977,
    2882,
    2804,
    1701,
    496,
    3875,
    291,
    2607,
    2731,
    1400,
    2544,
    496,
    1985,
    1402,
    1473,
    2804,
    2607,
    2731,
    3394,
    291,
    496,
    69,
    1646,
    1276,
    142,
    2607,
    3938,
    1701,
    1622,
    370,
    1213,
    1276,
    1400,
    1276,
    1213,
    -79,
    1400,
    2063,
    1400,
    2977,
    314,
    654,
    654,
    2977,
    315,
    173,
    3316,
    1400,
    3875,
    1985,
    3292,
    220,
    1400,
    2607,
    3938,
    291,
    3938,
    496,
    2819,
    3158,
    3938
  ],
  "triangulations": [
    [
      [
        62,
        72
      ],
      [
        50,
        52
      ],
      [
        42,
        48
      ],
      [
        10,
        43
      ],
      [
        13,
        42
      ],
      [
        30,
        55
      ],
      [
        10,
        61
      ],
      [
        22,
        35
      ],
      [
        12,
        34
      ],
      [
        57,
        66
      ],
      [
        31,
        47
      ],
      [
        6,
        57
      ],
      [
        31,
        56
      ],
      [
        22,
        53
      ],
      [
        6,
        66
      ],
      [
        55,
        68
      ],
      [
        28,
        51
      ],
      [
        4,
        66
      ],
      [
        18,
        28
      ],
      [
        35,
        44
      ],
      [
        26,
        32
      ],
      [
        15,
        32
      ],
      [
        25,
        43
      ],
      [
        3,
        70
      ],
      [
        9,
        65
      ],
      [
        0,
        7
      ],
      [
        60,
        76
      ],
      [
        14,
        33
      ],
      [
        32,
        69
      ],
      [
        22,
        46
      ],
      [
        24,
        65
      ],
      [
        13,
        74
      ],
      [
        14,
        51
      ],
      [
        24,
        37
      ],
      [
        16,
        33
      ],
      [
        37,
        65
      ],
      [
        16,
        42
      ],
      [
        11,
        55
      ],
      [
        22,
        30
      ],
      [
        38,
        48
      ],
      [
        5,
        78
      ],
      [
        9,
        12
      ],
      [
        23,
        38
      ],
      [
        14,
        35
      ],
      [
        40,
        54
      ],
      [
        18,
        51
      ],
      [
        24,
        67
      ],
      [
        32,
        71
      ],
      [
        49,
        66
      ],
      [
        19,
        34
      ],
      [
        2,
        27
      ],
      [
        22,
        60
      ],
      [
        33,
        42
      ],
      [
        39,
        76
      ],
      [
        45,
        62
      ],
      [
        31,
        72
      ],
      [
        16,
        35
      ],
      [
        59,
        70
      ],
      [
        37,
        67
      ],
      [
        20,
        26
      ],
      [
        36,
        77
      ],
      [
        32,
        55
      ],
      [
        4,
        18
      ],
      [
        43,
        64
      ],
      [
        9,
        78
      ],
      [
        24,
        78
      ],
      [
        13,
        23
      ],
      [
        16,
        74
      ],
      [
        33,
        35
      ],
      [
        47,
        52
      ],
      [
        63,
        70
      ],
      [
        0,
        32
      ],
      [
        8,
        45
      ],
      [
        59,
        63
      ],
      [
        25,
        40
      ],
      [
        28,
        57
      ],
      [
        45,
        73
      ],
      [
        11,
        50
      ],
      [
        12,
        15
      ],
      [
        29,
        31
      ],
      [
        46,
        47
      ],
      [
        37,
        69
      ],
      [
        3,
        76
      ],
      [
        0,
        59
      ],
      [
        2,
        56
      ],
      [
        46,
        56
      ],
      [
        30,
        63
      ],
      [
        35,
        53
      ],
      [
        35,
        62
      ],
      [
        23,
        42
      ],
      [
        41,
        78
      ],
      [
        19,
        20
      ],
      [
        26,
        77
      ],
      [
        53,
        61
      ],
      [
        17,
        50
      ],
      [
        30,
        47
      ],
      [
        9,
        55
      ],
      [
        11,
        52
      ],
      [
        26,
        34
      ],
      [
        35,
        46
      ],
      [
        12,
        26
      ],
      [
        32,
        59
      ],
      [
        40,
        42
      ],
      [
        21,
        29
      ],
      [
        32,
        68
      ],
      [
        1,
        7
      ],
      [
        19,
        77
      ],
      [
        4,
        40
      ],
      [
        18,
        57
      ],
      [
        24,
        73
      ],
      [
        27,
        35
      ],
      [
        18,
        66
      ],
      [
        27,
        44
      ],
      [
        5,
        41
      ],
      [
        47,
        56
      ],
      [
        73,
        75
      ],
      [
        29,
        72
      ],
      [
        40,
        66
      ],
      [
        5,
        50
      ],
      [
        17,
        52
      ],
      [
        12,
        65
      ],
      [
        58,
        62
      ],
      [
        23,
        74
      ],
      [
        12,
        19
      ],
      [
        26,
        36
      ],
      [
        33,
        51
      ],
      [
        21,
        31
      ],
      [
        61,
        76
      ],
      [
        12,
        37
      ],
      [
        6,
        51
      ],
      [
        16,
        53
      ],
      [
        4,
        33
      ],
      [
        35,
        66
      ],
      [
        1,
        64
      ],
      [
        43,
        70
      ],
      [
        7,
        59
      ],
      [
        8,
        24
      ],
      [
        25,
        74
      ],
      [
        9,
        32
      ],
      [
        54,
        64
      ],
      [
        10,
        39
      ],
      [
        40,
        74
      ],
      [
        32,
        36
      ],
      [
        11,
        47
      ],
      [
        37,
        75
      ],
      [
        38,
        40
      ],
      [
        6,
        35
      ],
      [
        60,
        70
      ],
      [
        32,
        63
      ],
      [
        50,
        78
      ],
      [
        42,
        74
      ],
      [
        65,
        78
      ],
      [
        3,
        39
      ],
      [
        17,
        47
      ],
      [
        41,
        50
      ],
      [
        6,
        28
      ],
      [
        60,
        63
      ],
      [
        44,
        46
      ],
      [
        69,
        75
      ],
      [
        10,
        53
      ],
      [
        39,
        43
      ],
      [
        7,
        54
      ],
      [
        10,
        16
      ],
      [
        17,
        31
      ],
      [
        39,
        61
      ],
      [
        10,
        25
      ],
      [
        2,
        21
      ],
      [
        19,
        37
      ],
      [
        21,
        56
      ],
      [
        63,
        71
      ],
      [
        4,
        49
      ],
      [
        22,
        63
      ],
      [
        50,
        55
      ],
      [
        24,
        45
      ],
      [
        27,
        62
      ],
      [
        1,
        43
      ],
      [
        55,
        78
      ],
      [
        70,
        76
      ],
      [
        35,
        45
      ],
      [
        8,
        58
      ],
      [
        1,
        70
      ],
      [
        36,
        37
      ],
      [
        22,
        47
      ],
      [
        3,
        43
      ],
      [
        29,
        62
      ],
      [
        4,
        42
      ],
      [
        45,
        58
      ],
      [
        38,
        74
      ],
      [
        6,
        14
      ],
      [
        15,
        26
      ],
      [
        20,
        77
      ],
      [
        16,
        25
      ],
      [
        5,
        58
      ],
      [
        67,
        73
      ],
      [
        55,
        71
      ],
      [
        2,
        44
      ],
      [
        69,
        79
      ],
      [
        1,
        54
      ],
      [
        17,
        72
      ],
      [
        18,
        49
      ],
      [
        20,
        34
      ],
      [
        9,
        68
      ],
      [
        2,
        62
      ],
      [
        8,
        78
      ],
      [
        25,
        64
      ],
      [
        23,
        48
      ],
      [
        40,
        64
      ],
      [
        7,
        70
      ],
      [
        53,
        76
      ],
      [
        67,
        75
      ],
      [
        58,
        72
      ],
      [
        18,
        33
      ],
      [
        36,
        69
      ],
      [
        2,
        46
      ],
      [
        5,
        8
      ],
      [
        37,
        77
      ],
      [
        5,
        72
      ],
      [
        30,
        71
      ],
      [
        5,
        17
      ],
      [
        9,
        15
      ],
      [
        40,
        48
      ],
      [
        75,
        79
      ],
      [
        11,
        30
      ],
      [
        21,
        62
      ],
      [
        53,
        60
      ]
    ],
    [
      [
        50,
        52
      ],
      [
        1,
        40
      ],
      [
        50,
        70
      ],
      [
        25,
        59
      ],
      [
        9,
        72
      ],
      [
        39,
        51
      ],
      [
        57,
        66
      ],
      [
        6,
        57
      ],
      [
        31,
        56
      ],
      [
        22,
        53
      ],
      [
        26,
        69
      ],
      [
        1,
        15
      ],
      [
        4,
        48
      ],
      [
        4,
        57
      ],
      [
        16,
        22
      ],
      [
        36,
        55
      ],
      [
        55,
        68
      ],
      [
        4,
        66
      ],
      [
        28,
        51
      ],
      [
        35,
        44
      ],
      [
        0,
        7
      ],
      [
        5,
        21
      ],
      [
        4,
        23
      ],
      [
        9,
        19
      ],
      [
        14,
        33
      ],
      [
        32,
        69
      ],
      [
        24,
        65
      ],
      [
        15,
        71
      ],
      [
        27,
        45
      ],
      [
        24,
        37
      ],
      [
        16,
        33
      ],
      [
        37,
        65
      ],
      [
        16,
        42
      ],
      [
        45,
        78
      ],
      [
        42,
        61
      ],
      [
        30,
        59
      ],
      [
        38,
        39
      ],
      [
        5,
        78
      ],
      [
        9,
        12
      ],
      [
        38,
        48
      ],
      [
        2,
        61
      ],
      [
        15,
        55
      ],
      [
        49,
        57
      ],
      [
        40,
        54
      ],
      [
        18,
        51
      ],
      [
        24,
        67
      ],
      [
        1,
        74
      ],
      [
        45,
        62
      ],
      [
        33,
        42
      ],
      [
        73,
        78
      ],
      [
        39,
        76
      ],
      [
        31,
        72
      ],
      [
        36,
        68
      ],
      [
        59,
        70
      ],
      [
        37,
        67
      ],
      [
        5,
        62
      ],
      [
        6,
        27
      ],
      [
        20,
        26
      ],
      [
        14,
        28
      ],
      [
        46,
        63
      ],
      [
        9,
        78
      ],
      [
        43,
        64
      ],
      [
        29,
        56
      ],
      [
        13,
        23
      ],
      [
        47,
        52
      ],
      [
        0,
        32
      ],
      [
        2,
        29
      ],
      [
        8,
        45
      ],
      [
        59,
        63
      ],
      [
        28,
        57
      ],
      [
        45,
        73
      ],
      [
        11,
        50
      ],
      [
        29,
        31
      ],
      [
        5,
        9
      ],
      [
        51,
        61
      ],
      [
        11,
        59
      ],
      [
        2,
        56
      ],
      [
        30,
        63
      ],
      [
        14,
        21
      ],
      [
        46,
        56
      ],
      [
        3,
        76
      ],
      [
        37,
        78
      ],
      [
        67,
        79
      ],
      [
        19,
        20
      ],
      [
        26,
        68
      ],
      [
        25,
        70
      ],
      [
        26,
        77
      ],
      [
        53,
        61
      ],
      [
        17,
        41
      ],
      [
        64,
        70
      ],
      [
        30,
        47
      ],
      [
        47,
        63
      ],
      [
        3,
        60
      ],
      [
        11,
        52
      ],
      [
        38,
        63
      ],
      [
        25,
        63
      ],
      [
        1,
        7
      ],
      [
        19,
        77
      ],
      [
        1,
        71
      ],
      [
        24,
        73
      ],
      [
        27,
        35
      ],
      [
        27,
        44
      ],
      [
        47,
        56
      ],
      [
        73,
        75
      ],
      [
        29,
        72
      ],
      [
        63,
        74
      ],
      [
        17,
        52
      ],
      [
        34,
        68
      ],
      [
        40,
        66
      ],
      [
        14,
        62
      ],
      [
        58,
        62
      ],
      [
        21,
        22
      ],
      [
        26,
        36
      ],
      [
        12,
        19
      ],
      [
        52,
        55
      ],
      [
        7,
        32
      ],
      [
        41,
        55
      ],
      [
        33,
        51
      ],
      [
        15,
        36
      ],
      [
        61,
        76
      ],
      [
        1,
        55
      ],
      [
        43,
        70
      ],
      [
        35,
        57
      ],
      [
        16,
        53
      ],
      [
        35,
        66
      ],
      [
        39,
        48
      ],
      [
        27,
        28
      ],
      [
        12,
        37
      ],
      [
        19,
        79
      ],
      [
        39,
        57
      ],
      [
        2,
        72
      ],
      [
        25,
        74
      ],
      [
        3,
        46
      ],
      [
        10,
        39
      ],
      [
        9,
        41
      ],
      [
        32,
        36
      ],
      [
        12,
        67
      ],
      [
        11,
        47
      ],
      [
        60,
        61
      ],
      [
        38,
        40
      ],
      [
        6,
        35
      ],
      [
        21,
        33
      ],
      [
        6,
        44
      ],
      [
        18,
        61
      ],
      [
        65,
        78
      ],
      [
        10,
        23
      ],
      [
        3,
        39
      ],
      [
        9,
        34
      ],
      [
        56,
        63
      ],
      [
        17,
        56
      ],
      [
        12,
        78
      ],
      [
        77,
        79
      ],
      [
        7,
        36
      ],
      [
        1,
        50
      ],
      [
        41,
        68
      ],
      [
        7,
        54
      ],
      [
        11,
        70
      ],
      [
        2,
        21
      ],
      [
        28,
        49
      ],
      [
        50,
        55
      ],
      [
        41,
        52
      ],
      [
        1,
        43
      ],
      [
        27,
        62
      ],
      [
        35,
        45
      ],
      [
        69,
        77
      ],
      [
        8,
        58
      ],
      [
        19,
        67
      ],
      [
        13,
        57
      ],
      [
        2,
        60
      ],
      [
        46,
        60
      ],
      [
        1,
        70
      ],
      [
        65,
        73
      ],
      [
        31,
        41
      ],
      [
        2,
        5
      ],
      [
        28,
        33
      ],
      [
        9,
        20
      ],
      [
        48,
        66
      ],
      [
        45,
        58
      ],
      [
        38,
        74
      ],
      [
        20,
        68
      ],
      [
        3,
        61
      ],
      [
        5,
        58
      ],
      [
        20,
        77
      ],
      [
        1,
        36
      ],
      [
        55,
        71
      ],
      [
        64,
        74
      ],
      [
        42,
        53
      ],
      [
        10,
        48
      ],
      [
        67,
        73
      ],
      [
        69,
        79
      ],
      [
        10,
        57
      ],
      [
        1,
        54
      ],
      [
        2,
        53
      ],
      [
        20,
        34
      ],
      [
        9,
        68
      ],
      [
        25,
        64
      ],
      [
        14,
        27
      ],
      [
        8,
        78
      ],
      [
        51,
        76
      ],
      [
        9,
        31
      ],
      [
        23,
        48
      ],
      [
        23,
        57
      ],
      [
        3,
        63
      ],
      [
        1,
        38
      ],
      [
        52,
        56
      ],
      [
        27,
        57
      ],
      [
        41,
        56
      ],
      [
        36,
        69
      ],
      [
        67,
        75
      ],
      [
        18,
        33
      ],
      [
        2,
        46
      ],
      [
        18,
        42
      ],
      [
        5,
        8
      ],
      [
        5,
        72
      ],
      [
        22,
        33
      ],
      [
        10,
        13
      ],
      [
        39,
        49
      ],
      [
        40,
        48
      ],
      [
        49,
        51
      ],
      [
        75,
        79
      ],
      [
        43,
        74
      ],
      [
        3,
        38
      ],
      [
        21,
        53
      ],
      [
        11,
        30
      ],
      [
        21,
        62
      ]
    ]
  ],
  "coreset_weights": [
    2,
    1
  ]
}